{"compliant_example_ids":[],"effective_in":"1.0.0-rc.1","enforcement":"independent_review","evidence":["standards/enterprise/mobile-security.md and the final joined AI consistency review"],"examples_required":false,"exception_policy":"A broader origin, navigation, or bridge capability requires human Security approval, exact scope, isolation controls, owner, expiry, and removal plan.","id":"MSEC-WEB-001","introduced_in":"1.0.0-rc.1","level":"must","lifecycle":"active","non_compliant_example_ids":[],"profile_ids":["core"],"rationale_adrs":["ADR-0002"],"risk_class":"critical","schema_version":1,"scope":["WKWebView origins","WebView navigation","native JavaScript bridges","embedded web content"],"severity":"critical","statement":"Embedded web content uses allowlisted origins and navigation, the minimum enabled capability set, isolated privileged content, narrow bridge handlers, and closed validation of every native-bridge message."}
